[{"Category": "Fashion", "Brand": "M", "Size Chart": "M", "Colour Name": "O", "Care Instructions": "O", "Weight": "O", "Length": "O", "Breadth": "O", "Height": "O", "Bundles": "O", "Max Sale Quantity": "O", "Num Pockets": "O", "Reversible": "O", "Fragile": "O", "Liquid": "O", "Hazardous": "O", "Sub-Category": "Shirts", "Gender": "M", "Colour": "M", "Size": "M", "Fabric": "M", "Sport Type": "O", "Wash Type": "O", "Features": "O", "Fabric Finish": "O", "Material": "O", "Material Finish": "O", "Pattern": "O", "Occasion": "O", "Season": "O", "Trend": "O", "Fit": "O", "Collar": "O", "Neck": "O", "Sleeve Length": "O"}, {"Category": "Fashion", "Brand": "M", "Size Chart": "M", "Colour Name": "O", "Care Instructions": "O", "Weight": "O", "Length": "O", "Breadth": "O", "Height": "O", "Bundles": "O", "Max Sale Quantity": "O", "Num Pockets": "O", "Fragile": "O", "Liquid": "O", "Hazardous": "O", "Sustainability": "O", "Sub-Category": "T Shirts", "Gender": "M", "Colour": "M", "Size": "M", "Fabric": "M", "Sport Type": "O", "Wash Type": "O", "Features": "O", "Fabric Finish": "O", "Material": "O", "Material Finish": "O", "Pattern": "O", "Occasion": "O", "Season": "O", "Trend": "O", "Fit": "O", "Collar": "O", "Neck": "O", "Sleeve Length": "O"}, {"Category": "Fashion", "Brand": "M", "Size Chart": "M", "Colour Name": "O", "Care Instructions": "O", "Weight": "O", "Length": "O", "Breadth": "O", "Height": "O", "Bundles": "O", "Max Sale Quantity": "O", "Lining": "O", "Num Pockets": "O", "Reversible": "O", "Fragile": "O", "Liquid": "O", "Hazardous": "O", "Sub-Category": "Sweatshirts", "Gender": "M", "Colour": "M", "Size": "M", "Fabric": "M", "Sport Type": "O", "Wash Type": "O", "Features": "O", "Fabric Finish": "O", "Material": "O", "Material Finish": "O", "Pattern": "O", "Occasion": "O", "Season": "O", "Trend": "O", "Fit": "O", "Collar": "O", "Neck": "O", "Sleeve Length": "O", "Sweatshirt Type": "O", "Waist Rise": "O"}, {"Category": "Fashion", "Brand": "M", "Size Chart": "M", "Colour Name": "O", "Care Instructions": "O", "Weight": "O", "Length": "O", "Breadth": "O", "Height": "O", "Bundles": "O", "Max Sale Quantity": "O", "Lining": "O", "Num Pockets": "O", "Fragile": "O", "Liquid": "O", "Hazardous": "O", "Sustainability": "O", "Handcrafted": "O", "Craftmark": "O", "Sub-Category": "Kurtas & Kurta Sets", "Gender": "M", "Colour": "M", "Size": "M", "Fabric": "M", "Wash Type": "O", "Features": "O", "Fabric Finish": "O", "Material": "O", "Material Finish": "O", "Pattern": "O", "Occasion": "O", "Season": "O", "Trend": "O", "Fit": "O", "Collar": "O", "Neck": "O", "Sleeve Length": "O", "Ornamentation": "O"}, {"Category": "Fashion", "Brand": "M", "Size Chart": "M", "Colour Name": "O", "Care Instructions": "O", "Weight": "O", "Length": "O", "Breadth": "O", "Height": "O", "Bundles": "O", "Max Sale Quantity": "O", "Lining": "O", "Num Pockets": "O", "Reversible": "O", "Fragile": "O", "Liquid": "O", "Hazardous": "O", "Sustainability": "O", "Handcrafted": "O", "Craftmark": "O", "Sub-Category": "Jackets & Coats", "Gender": "M", "Colour": "M", "Size": "M", "Fabric": "M", "Sport Type": "O", "Wash Type": "O", "Features": "O", "Fabric Finish": "O", "Material": "O", "Material Finish": "O", "Pattern": "O", "Occasion": "O", "Season": "O", "Trend": "O", "Fit": "O", "Collar": "O", "Neck": "O", "Front Styling": "O", "Sleeve Length": "O"}, {"Category": "Fashion", "Brand": "M", "Size Chart": "M", "Colour Name": "O", "Care Instructions": "O", "Weight": "O", "Length": "O", "Breadth": "O", "Height": "O", "Bundles": "O", "Max Sale Quantity": "O", "Num Pockets": "O", "Reversible": "O", "Fragile": "O", "Liquid": "O", "Hazardous": "O", "Sub-Category": "Sweaters", "Gender": "M", "Colour": "M", "Size": "M", "Fabric": "M", "Sport Type": "O", "Wash Type": "O", "Features": "O", "Fabric Finish": "O", "Material": "O", "Material Finish": "O", "Pattern": "O", "Occasion": "O", "Season": "O", "Trend": "O", "Fit": "O", "Collar": "O", "Neck": "O", "Sleeve Length": "O"}, {"Category": "Fashion", "Brand": "M", "Size Chart": "M", "Colour Name": "O", "Care Instructions": "O", "Weight": "O", "Length": "O", "Breadth": "O", "Height": "O", "Bundles": "O", "Max Sale Quantity": "O", "Lining": "O", "Num Pockets": "O", "Fragile": "O", "Liquid": "O", "Hazardous": "O", "Sub-Category": "Suits", "Gender": "M", "Colour": "M", "Size": "M", "Fabric": "M", "Wash Type": "O", "Features": "O", "Fabric Finish": "O", "Material": "O", "Material Finish": "O", "Pattern": "O", "Occasion": "O", "Season": "O", "Trend": "O", "Fit": "O", "Collar": "O", "Neck": "O", "Front Styling": "O", "Sleeve Length": "O", "Ornamentation": "O"}, {"Category": "Fashion", "Brand": "M", "Size Chart": "M", "Colour Name": "O", "Care Instructions": "O", "Weight": "O", "Length": "O", "Breadth": "O", "Height": "O", "Bundles": "O", "Max Sale Quantity": "O", "Fragile": "O", "Liquid": "O", "Hazardous": "O", "Sustainability": "O", "Handcrafted": "O", "Craftmark": "O", "Sub-Category": "Sherwanis", "Gender": "M", "Colour": "M", "Size": "M", "Fabric": "M", "Wash Type": "O", "Features": "O", "Fabric Finish": "O", "Material": "O", "Material Finish": "O", "Pattern": "O", "Occasion": "O", "Season": "O", "Trend": "O", "Fit": "O", "Collar": "O", "Neck": "O", "Sleeve Length": "O"}, {"Category": "Fashion", "Brand": "M", "Size Chart": "M", "Colour Name": "O", "Care Instructions": "O", "Weight": "O", "Length": "O", "Breadth": "O", "Height": "O", "Bundles": "O", "Max Sale Quantity": "O", "Num Pockets": "O", "Fragile": "O", "Liquid": "O", "Hazardous": "O", "Sub-Category": "Track Shirts", "Gender": "M", "Colour": "M", "Size": "M", "Fabric": "M", "Sport Type": "O", "Wash Type": "O", "Features": "O", "Fabric Finish": "O", "Material": "O", "Material Finish": "O", "Pattern": "O", "Occasion": "O", "Season": "O", "Trend": "O", "Fit": "O", "Collar": "O", "Neck": "O", "Sleeve Length": "O"}, {"Category": "Fashion", "Brand": "M", "Size Chart": "M", "Colour Name": "O", "Care Instructions": "O", "Weight": "O", "Length": "O", "Breadth": "O", "Height": "O", "Bundles": "O", "Max Sale Quantity": "O", "Num Pockets": "O", "Fragile": "O", "Liquid": "O", "Hazardous": "O", "Sub-Category": "Track Suits", "Gender": "M", "Colour": "M", "Size": "M", "Fabric": "M", "Sport Type": "O", "Wash Type": "O", "Features": "O", "Fabric Finish": "O", "Material": "O", "Material Finish": "O", "Pattern": "O", "Occasion": "O", "Season": "O", "Trend": "O", "Fit": "O", "Collar": "O", "Neck": "O", "Sleeve Length": "O"}, {"Category": "Fashion", "Brand": "M", "Colour Name": "O", "Care Instructions": "O", "Weight": "O", "Length": "O", "Breadth": "O", "Height": "O", "Bundles": "O", "Max Sale Quantity": "O", "Fragile": "O", "Liquid": "O", "Hazardous": "O", "Sustainability": "O", "Handcrafted": "O", "Craftmark": "O", "Sub-Category": "Unstitched Fabrics", "Gender": "M", "Colour": "M", "Size": "M", "Fabric": "M", "Wash Type": "O", "Features": "O", "Fabric Finish": "O", "Material": "O", "Material Finish": "O", "Pattern": "O", "Occasion": "O", "Season": "O", "Trend": "O", "Fit": "O"}, {"Category": "Fashion", "Brand": "M", "Size Chart": "M", "Colour Name": "O", "Care Instructions": "O", "Weight": "O", "Length": "O", "Breadth": "O", "Height": "O", "Bundles": "O", "Max Sale Quantity": "O", "Num Pockets": "O", "Fragile": "O", "Liquid": "O", "Hazardous": "O", "Sustainability": "O", "Handcrafted": "O", "Craftmark": "O", "Sub-Category": "Dresses", "Gender": "M", "Colour": "M", "Size": "M", "Fabric": "M", "Sport Type": "O", "Wash Type": "O", "Features": "O", "Fabric Finish": "O", "Material": "O", "Material Finish": "O", "Pattern": "O", "Occasion": "O", "Season": "O", "Trend": "O", "Fit": "O", "Collar": "O", "Neck": "O", "Sleeve Length": "O"}, {"Category": "Fashion", "Brand": "M", "Size Chart": "M", "Colour Name": "O", "Care Instructions": "O", "Weight": "O", "Length": "O", "Breadth": "O", "Height": "O", "Bundles": "O", "Max Sale Quantity": "O", "Num Pockets": "O", "Reversible": "O", "Fragile": "O", "Liquid": "O", "Hazardous": "O", "Sustainability": "O", "Handcrafted": "O", "Craftmark": "O", "Sub-Category": "Tops", "Gender": "M", "Colour": "M", "Size": "M", "Fabric": "M", "Sport Type": "O", "Wash Type": "O", "Features": "O", "Fabric Finish": "O", "Material": "O", "Material Finish": "O", "Pattern": "O", "Occasion": "O", "Season": "O", "Trend": "O", "Fit": "O", "Collar": "O", "Neck": "O", "Top Type": "O", "Sleeve Length": "O"}, {"Category": "Fashion", "Brand": "M", "Size Chart": "M", "Colour Name": "O", "Care Instructions": "O", "Weight": "O", "Length": "O", "Breadth": "O", "Height": "O", "Bundles": "O", "Max Sale Quantity": "O", "Num Pockets": "O", "Fragile": "O", "Liquid": "O", "Hazardous": "O", "Sub-Category": "Trousers", "Gender": "M", "Colour": "M", "Size": "M", "Fabric": "M", "Sport Type": "O", "Wash Type": "O", "Features": "O", "Fabric Finish": "O", "Material": "O", "Material Finish": "O", "Pattern": "O", "Occasion": "O", "Season": "O", "Trend": "O", "Fit": "O", "Collar": "O", "Neck": "O", "Bottom Type": "O", "Sleeve Length": "O", "Waist Rise": "O"}, {"Category": "Fashion", "Brand": "M", "Size Chart": "M", "Colour Name": "O", "Care Instructions": "O", "Weight": "O", "Length": "O", "Breadth": "O", "Height": "O", "Bundles": "O", "Max Sale Quantity": "O", "Num Pockets": "O", "Fragile": "O", "Liquid": "O", "Hazardous": "O", "Sub-Category": "Capris", "Gender": "M", "Colour": "M", "Size": "M", "Fabric": "M", "Sport Type": "O", "Wash Type": "O", "Features": "O", "Fabric Finish": "O", "Material": "O", "Material Finish": "O", "Pattern": "O", "Occasion": "O", "Season": "O", "Trend": "O", "Fit": "O", "Collar": "O", "Neck": "O", "Bottom Type": "O", "Sleeve Length": "O", "Waist Rise": "O"}, {"Category": "Fashion", "Brand": "M", "Size Chart": "M", "Colour Name": "O", "Care Instructions": "O", "Weight": "O", "Length": "O", "Breadth": "O", "Height": "O", "Bundles": "O", "Max Sale Quantity": "O", "Num Pockets": "O", "Fragile": "O", "Liquid": "O", "Hazardous": "O", "Sub-Category": "Coordinates", "Gender": "M", "Colour": "M", "Size": "M", "Fabric": "M", "Sport Type": "O", "Wash Type": "O", "Features": "O", "Fabric Finish": "O", "Material": "O", "Material Finish": "O", "Pattern": "O", "Occasion": "O", "Season": "O", "Trend": "O", "Fit": "O", "Collar": "O", "Neck": "O", "Sleeve Length": "O"}, {"Category": "Fashion", "Brand": "M", "Size Chart": "M", "Colour Name": "O", "Care Instructions": "O", "Weight": "O", "Length": "O", "Breadth": "O", "Height": "O", "Bundles": "O", "Max Sale Quantity": "O", "Num Pockets": "O", "Fragile": "O", "Liquid": "O", "Hazardous": "O", "Sub-Category": "Playsuits", "Gender": "M", "Colour": "M", "Size": "M", "Fabric": "M", "Sport Type": "O", "Wash Type": "O", "Features": "O", "Fabric Finish": "O", "Material": "O", "Material Finish": "O", "Pattern": "O", "Occasion": "O", "Season": "O", "Trend": "O", "Fit": "O", "Collar": "O", "Neck": "O", "Sleeve Length": "O"}, {"Category": "Fashion", "Brand": "M", "Size Chart": "M", "Colour Name": "O", "Care Instructions": "O", "Weight": "O", "Length": "O", "Breadth": "O", "Height": "O", "Bundles": "O", "Max Sale Quantity": "O", "Num Pockets": "O", "Fragile": "O", "Liquid": "O", "Hazardous": "O", "Sub-Category": "Jumpsuits", "Gender": "M", "Colour": "M", "Size": "M", "Fabric": "M", "Sport Type": "O", "Wash Type": "O", "Features": "O", "Fabric Finish": "O", "Material": "O", "Material Finish": "O", "Pattern": "O", "Occasion": "O", "Season": "O", "Trend": "O", "Fit": "O", "Collar": "O", "Neck": "O", "Sleeve Length": "O"}, {"Category": "Fashion", "Brand": "M", "Size Chart": "M", "Colour Name": "O", "Care Instructions": "O", "Weight": "O", "Length": "O", "Breadth": "O", "Height": "O", "Bundles": "O", "Max Sale Quantity": "O", "Num Pockets": "O", "Fragile": "O", "Liquid": "O", "Hazardous": "O", "Sub-Category": "Shrugs & Blouses", "Gender": "M", "Colour": "M", "Size": "M", "Fabric": "M", "Sport Type": "O", "Wash Type": "O", "Features": "O", "Fabric Finish": "O", "Material": "O", "Material Finish": "O", "Pattern": "O", "Occasion": "O", "Season": "O", "Trend": "O", "Fit": "O", "Collar": "O", "Neck": "O", "Sleeve Length": "O"}, {"Category": "Fashion", "Brand": "M", "Size Chart": "M", "Colour Name": "O", "Care Instructions": "O", "Weight": "O", "Length": "O", "Breadth": "O", "Height": "O", "Bundles": "O", "Max Sale Quantity": "O", "Num Pockets": "O", "Reversible": "O", "Fragile": "O", "Liquid": "O", "Hazardous": "O", "Sub-Category": "Blazers & Waistcoats", "Gender": "M", "Colour": "M", "Size": "M", "Fabric": "M", "Sport Type": "O", "Wash Type": "O", "Features": "O", "Fabric Finish": "O", "Material": "O", "Material Finish": "O", "Pattern": "O", "Occasion": "O", "Season": "O", "Trend": "O", "Fit": "O", "Collar": "O", "Neck": "O", "Sleeve Length": "O"}, {"Category": "Fashion", "Brand": "M", "Size Chart": "M", "Colour Name": "O", "Care Instructions": "O", "Weight": "O", "Length": "O", "Breadth": "O", "Height": "O", "Bundles": "O", "Max Sale Quantity": "O", "Num Pockets": "O", "Fragile": "O", "Liquid": "O", "Hazardous": "O", "Sub-Category": "Tights, Leggings & Jeggings", "Gender": "M", "Colour": "M", "Size": "M", "Fabric": "M", "Sport Type": "O", "Wash Type": "O", "Features": "O", "Fabric Finish": "O", "Material": "O", "Material Finish": "O", "Pattern": "O", "Occasion": "O", "Season": "O", "Trend": "O", "Fit": "O", "Collar": "O", "Neck": "O", "Sleeve Length": "O"}, {"Category": "Fashion", "Brand": "M", "Size Chart": "M", "Colour Name": "O", "Care Instructions": "O", "Weight": "O", "Length": "O", "Breadth": "O", "Height": "O", "Bundles": "O", "Max Sale Quantity": "O", "Num Pockets": "O", "Fragile": "O", "Liquid": "O", "Hazardous": "O", "Sub-Category": "Track Pants", "Gender": "M", "Colour": "M", "Size": "M", "Fabric": "M", "Sport Type": "O", "Wash Type": "O", "Features": "O", "Fabric Finish": "O", "Material": "O", "Material Finish": "O", "Pattern": "O", "Occasion": "O", "Season": "O", "Trend": "O", "Fit": "O", "Collar": "O", "Neck": "O", "Sleeve Length": "O"}, {"Category": "Fashion", "Brand": "M", "Size Chart": "M", "Colour Name": "O", "Care Instructions": "O", "Weight": "O", "Length": "O", "Breadth": "O", "Height": "O", "Bundles": "O", "Max Sale Quantity": "O", "Num Pockets": "O", "Fragile": "O", "Liquid": "O", "Hazardous": "O", "Sub-Category": "Jeans", "Gender": "M", "Colour": "M", "Size": "M", "Fabric": "M", "Sport Type": "O", "Wash Type": "O", "Features": "O", "Fabric Finish": "O", "Material": "O", "Material Finish": "O", "Pattern": "O", "Occasion": "O", "Season": "O", "Trend": "O", "Fit": "O", "Collar": "O", "Neck": "O", "Sleeve Length": "O", "Waist Rise": "O"}, {"Category": "Fashion", "Brand": "M", "Size Chart": "M", "Colour Name": "O", "Care Instructions": "O", "Weight": "O", "Length": "O", "Breadth": "O", "Height": "O", "Bundles": "O", "Max Sale Quantity": "O", "Num Pockets": "O", "Fragile": "O", "Liquid": "O", "Hazardous": "O", "Sub-Category": "Shorts", "Gender": "M", "Colour": "M", "Size": "M", "Fabric": "M", "Sport Type": "O", "Wash Type": "O", "Features": "O", "Fabric Finish": "O", "Material": "O", "Material Finish": "O", "Pattern": "O", "Occasion": "O", "Season": "O", "Trend": "O", "Fit": "O"}, {"Category": "Fashion", "Brand": "M", "Size Chart": "M", "Colour Name": "O", "Care Instructions": "O", "Weight": "O", "Length": "O", "Breadth": "O", "Height": "O", "Bundles": "O", "Max Sale Quantity": "O", "Num Pockets": "O", "Fragile": "O", "Liquid": "O", "Hazardous": "O", "Sub-Category": "Joggers", "Gender": "M", "Colour": "M", "Size": "M", "Fabric": "M", "Wash Type": "O", "Features": "O", "Fabric Finish": "O", "Material": "O", "Material Finish": "O", "Pattern": "O", "Occasion": "O", "Season": "O", "Trend": "O", "Fit": "O"}, {"Category": "Fashion", "Brand": "M", "Size Chart": "M", "Colour Name": "O", "Care Instructions": "O", "Weight": "O", "Length": "O", "Breadth": "O", "Height": "O", "Bundles": "O", "Max Sale Quantity": "O", "Num Pockets": "O", "Fragile": "O", "Liquid": "O", "Hazardous": "O", "Sub-Category": "Dhotis & Dhoti Pants", "Gender": "M", "Colour": "M", "Size": "M", "Fabric": "M", "Wash Type": "O", "Features": "O", "Fabric Finish": "O", "Material": "O", "Material Finish": "O", "Pattern": "O", "Occasion": "O", "Season": "O", "Trend": "O", "Fit": "O"}, {"Category": "Fashion", "Brand": "M", "Size Chart": "M", "Colour Name": "O", "Care Instructions": "O", "Weight": "O", "Length": "O", "Breadth": "O", "Height": "O", "Bundles": "O", "Max Sale Quantity": "O", "Num Pockets": "O", "Fragile": "O", "Liquid": "O", "Hazardous": "O", "Sustainability": "O", "Handcrafted": "O", "Craftmark": "O", "Sub-Category": "Churidars", "Gender": "M", "Colour": "M", "Size": "M", "Fabric": "M", "Wash Type": "O", "Features": "O", "Fabric Finish": "O", "Material": "O", "Material Finish": "O", "Pattern": "O", "Occasion": "O", "Season": "O", "Trend": "O", "Fit": "O"}, {"Category": "Fashion", "Brand": "M", "Size Chart": "M", "Colour Name": "O", "Care Instructions": "O", "Weight": "O", "Length": "O", "Breadth": "O", "Height": "O", "Bundles": "O", "Max Sale Quantity": "O", "Num Pockets": "O", "Fragile": "O", "Liquid": "O", "Hazardous": "O", "Sustainability": "O", "Handcrafted": "O", "Craftmark": "O", "Sub-Category": "Salwars", "Gender": "M", "Colour": "M", "Size": "M", "Fabric": "M", "Wash Type": "O", "Features": "O", "Fabric Finish": "O", "Material": "O", "Material Finish": "O", "Pattern": "O", "Occasion": "O", "Season": "O", "Trend": "O", "Fit": "O", "Hemline": "O"}, {"Category": "Fashion", "Brand": "M", "Size Chart": "M", "Colour Name": "O", "Care Instructions": "O", "Weight": "O", "Length": "O", "Breadth": "O", "Height": "O", "Bundles": "O", "Max Sale Quantity": "O", "Num Pockets": "O", "Fragile": "O", "Liquid": "O", "Hazardous": "O", "Sub-Category": "Dungarees & Jumpsuits", "Gender": "M", "Colour": "M", "Size": "M", "Fabric": "M", "Wash Type": "O", "Features": "O", "Fabric Finish": "O", "Material": "O", "Material Finish": "O", "Pattern": "O", "Occasion": "O", "Season": "O", "Trend": "O", "Fit": "O", "Collar": "O", "Neck": "O", "Sleeve Length": "O"}, {"Category": "Fashion", "Brand": "M", "Size Chart": "M", "Colour Name": "O", "Care Instructions": "O", "Weight": "O", "Length": "O", "Breadth": "O", "Height": "O", "Bundles": "O", "Max Sale Quantity": "O", "Num Pockets": "O", "Fragile": "O", "Liquid": "O", "Hazardous": "O", "Sub-Category": "Skirts", "Gender": "M", "Colour": "M", "Size": "M", "Fabric": "M", "Sport Type": "O", "Wash Type": "O", "Features": "O", "Fabric Finish": "O", "Material": "O", "Material Finish": "O", "Pattern": "O", "Occasion": "O", "Season": "O", "Trend": "O", "Fit": "O", "Collar": "O", "Neck": "O", "Hemline": "O", "Sleeve Length": "O", "Waist Rise": "O"}, {"Category": "Fashion", "Brand": "M", "Size Chart": "M", "Colour Name": "O", "Care Instructions": "O", "Weight": "O", "Length": "O", "Breadth": "O", "Height": "O", "Bundles": "O", "Max Sale Quantity": "O", "Num Pockets": "O", "Fragile": "O", "Liquid": "O", "Hazardous": "O", "Sub-Category": "Clothing Sets", "Gender": "M", "Colour": "M", "Size": "M", "Fabric": "M", "Wash Type": "O", "Features": "O", "Fabric Finish": "O", "Material": "O", "Material Finish": "O", "Pattern": "O", "Occasion": "O", "Season": "O", "Trend": "O", "Fit": "O", "Collar": "O", "Neck": "O", "Sleeve Length": "O"}, {"Category": "Fashion", "Brand": "M", "Size Chart": "M", "Colour Name": "O", "Care Instructions": "O", "Weight": "O", "Length": "O", "Breadth": "O", "Height": "O", "Bundles": "O", "Reversible": "M", "Fragile": "O", "Liquid": "O", "Hazardous": "O", "Sub-Category": "Belts", "Gender": "M", "Colour": "M", "Size": "M", "Features": "O", "Material": "M", "Material Finish": "O", "Pattern": "O", "Occasion": "O", "Season": "O", "Trend": "O", "Buckle Material": "O", "Buckle Type": "O"}, {"Category": "Fashion", "Brand": "M", "Colour Name": "O", "Care Instructions": "O", "Weight": "O", "Length": "O", "Breadth": "O", "Height": "O", "Bundles": "O", "Fragile": "O", "Liquid": "O", "Hazardous": "O", "Sub-Category": "Caps & Hats", "Gender": "M", "Colour": "M", "Size": "M", "Features": "O", "Material": "M", "Material Finish": "O", "Pattern": "O", "Occasion": "O", "Season": "O", "Trend": "O"}, {"Category": "Fashion", "Brand": "M", "Size Chart": "M", "Colour Name": "O", "Care Instructions": "O", "Weight": "O", "Length": "O", "Breadth": "O", "Height": "O", "Bundles": "O", "Max Sale Quantity": "O", "Lining": "O", "Num Pockets": "O", "Fragile": "O", "Liquid": "O", "Hazardous": "O", "Sustainability": "O", "Handcrafted": "O", "Craftmark": "O", "Sub-Category": "Kurtis, Tunics", "Gender": "M", "Colour": "M", "Size": "M", "Fabric": "M", "Wash Type": "O", "Features": "O", "Fabric Finish": "O", "Material": "O", "Material Finish": "O", "Pattern": "O", "Occasion": "O", "Season": "O", "Trend": "O", "Fit": "O", "Collar": "O", "Neck": "O", "Hemline": "O", "Sleeve Length": "O", "Ornamentation": "O"}, {"Category": "Fashion", "Brand": "M", "Size Chart": "M", "Colour Name": "O", "Care Instructions": "O", "Weight": "O", "Length": "O", "Breadth": "O", "Height": "O", "Bundles": "O", "Max Sale Quantity": "O", "Lining": "O", "Fragile": "O", "Liquid": "O", "Hazardous": "O", "Sustainability": "O", "Handcrafted": "O", "Craftmark": "O", "Sub-Category": "Sarees", "Gender": "M", "Colour": "M", "Size": "M", "Fabric": "M", "Wash Type": "O", "Features": "O", "Fabric Finish": "O", "Material": "O", "Material Finish": "O", "Pattern": "O", "Occasion": "O", "Season": "O", "Trend": "O", "Fit": "O", "Collar": "O", "Neck": "O", "Sleeve Length": "O", "Ornamentation": "O"}, {"Category": "Fashion", "Brand": "M", "Size Chart": "M", "Colour Name": "O", "Care Instructions": "O", "Weight": "O", "Length": "O", "Breadth": "O", "Height": "O", "Bundles": "O", "Max Sale Quantity": "O", "Lining": "O", "Num Pockets": "O", "Fragile": "O", "Liquid": "O", "Hazardous": "O", "Sustainability": "O", "Handcrafted": "O", "Craftmark": "O", "Sub-Category": "Ethnic Wear", "Gender": "M", "Colour": "M", "Size": "M", "Fabric": "M", "Wash Type": "O", "Features": "O", "Fabric Finish": "O", "Material": "O", "Material Finish": "O", "Pattern": "O", "Occasion": "O", "Season": "O", "Trend": "O", "Fit": "O", "Collar": "O", "Neck": "O", "Sleeve Length": "O", "Ornamentation": "O"}, {"Category": "Fashion", "Brand": "M", "Size Chart": "M", "Colour Name": "O", "Care Instructions": "O", "Weight": "O", "Length": "O", "Breadth": "O", "Height": "O", "Bundles": "O", "Max Sale Quantity": "O", "Lining": "O", "Fragile": "O", "Liquid": "O", "Hazardous": "O", "Sustainability": "O", "Handcrafted": "O", "Craftmark": "O", "Sub-Category": "Palazzos", "Gender": "M", "Colour": "M", "Size": "M", "Fabric": "M", "Wash Type": "O", "Features": "O", "Fabric Finish": "O", "Material": "O", "Material Finish": "O", "Pattern": "O", "Occasion": "O", "Season": "O", "Trend": "O", "Fit": "O", "Collar": "O", "Neck": "O", "Hemline": "O", "Sleeve Length": "O", "Ornamentation": "O"}, {"Category": "Fashion", "Brand": "M", "Size Chart": "M", "Colour Name": "O", "Care Instructions": "O", "Weight": "O", "Length": "O", "Breadth": "O", "Height": "O", "Bundles": "O", "Max Sale Quantity": "O", "Lining": "O", "Fragile": "O", "Liquid": "O", "Hazardous": "O", "Sustainability": "O", "Handcrafted": "O", "Craftmark": "O", "Sub-Category": "Dress Materials", "Gender": "M", "Colour": "M", "Size": "M", "Fabric": "M", "Wash Type": "O", "Features": "O", "Fabric Finish": "O", "Material": "O", "Material Finish": "O", "Pattern": "O", "Occasion": "O", "Season": "O", "Trend": "O", "Fit": "O", "Collar": "O", "Neck": "O", "Sleeve Length": "O", "Ornamentation": "O"}, {"Category": "Fashion", "Brand": "M", "Size Chart": "M", "Colour Name": "O", "Care Instructions": "O", "Weight": "O", "Length": "O", "Breadth": "O", "Height": "O", "Bundles": "O", "Max Sale Quantity": "O", "Lining": "O", "Fragile": "O", "Liquid": "O", "Hazardous": "O", "Sustainability": "O", "Handcrafted": "O", "Craftmark": "O", "Sub-Category": "Lehenga Cholis", "Gender": "M", "Colour": "M", "Size": "M", "Fabric": "M", "Wash Type": "O", "Features": "O", "Fabric Finish": "O", "Material": "O", "Material Finish": "O", "Pattern": "O", "Occasion": "O", "Season": "O", "Trend": "O", "Fit": "O", "Collar": "O", "Neck": "O", "Hemline": "O", "Sleeve Length": "O", "Ornamentation": "O"}, {"Category": "Fashion", "Brand": "M", "Size Chart": "M", "Colour Name": "O", "Care Instructions": "O", "Weight": "O", "Length": "O", "Breadth": "O", "Height": "O", "Bundles": "O", "Max Sale Quantity": "O", "Lining": "O", "Fragile": "O", "Liquid": "O", "Hazardous": "O", "Sustainability": "O", "Handcrafted": "O", "Craftmark": "O", "Sub-Category": "Dupattas & Shawls", "Gender": "M", "Colour": "M", "Size": "M", "Fabric": "M", "Wash Type": "O", "Features": "O", "Fabric Finish": "O", "Material": "O", "Material Finish": "O", "Pattern": "O", "Occasion": "O", "Season": "O", "Trend": "O", "Fit": "O", "Collar": "O", "Neck": "O", "Sleeve Length": "O", "Ornamentation": "O"}, {"Category": "Fashion", "Brand": "M", "Size Chart": "M", "Colour Name": "O", "Care Instructions": "O", "Weight": "O", "Length": "O", "Breadth": "O", "Height": "O", "Bundles": "O", "Max Sale Quantity": "O", "Lining": "O", "Fragile": "O", "Liquid": "O", "Hazardous": "O", "Sustainability": "O", "Handcrafted": "O", "Craftmark": "O", "Sub-Category": "Burqas & Hijabs", "Gender": "M", "Colour": "M", "Size": "M", "Fabric": "M", "Wash Type": "O", "Features": "O", "Fabric Finish": "O", "Material": "O", "Material Finish": "O", "Pattern": "O", "Occasion": "O", "Season": "O", "Trend": "O", "Fit": "O", "Collar": "O", "Neck": "O", "Sleeve Length": "O", "Ornamentation": "O"}, {"Category": "Fashion", "Brand": "M", "Size Chart": "M", "Colour Name": "O", "Care Instructions": "O", "Weight": "O", "Length": "O", "Breadth": "O", "Height": "O", "Bundles": "O", "Max Sale Quantity": "O", "Lining": "O", "Fragile": "O", "Liquid": "O", "Hazardous": "O", "Sustainability": "O", "Handcrafted": "O", "Craftmark": "O", "Sub-Category": "Blouses", "Gender": "M", "Colour": "M", "Size": "M", "Fabric": "M", "Wash Type": "O", "Features": "O", "Fabric Finish": "O", "Material": "O", "Material Finish": "O", "Pattern": "O", "Occasion": "O", "Season": "O", "Trend": "O", "Fit": "O", "Collar": "O", "Neck": "O", "Sleeve Length": "O", "Ornamentation": "O"}, {"Category": "Fashion", "Brand": "M", "Size Chart": "M", "Colour Name": "O", "Care Instructions": "O", "Weight": "O", "Length": "O", "Breadth": "O", "Height": "O", "Bundles": "O", "Max Sale Quantity": "O", "Lining": "O", "Fragile": "O", "Liquid": "O", "Hazardous": "O", "Sustainability": "O", "Handcrafted": "O", "Craftmark": "O", "Sub-Category": "Blouse Pieces", "Gender": "M", "Colour": "M", "Size": "M", "Fabric": "M", "Wash Type": "O", "Features": "O", "Fabric Finish": "O", "Material": "O", "Material Finish": "O", "Pattern": "O", "Occasion": "O", "Season": "O", "Trend": "O", "Fit": "O", "Collar": "O", "Neck": "O", "Sleeve Length": "O", "Ornamentation": "O"}, {"Category": "Fashion", "Brand": "M", "Size Chart": "M", "Colour Name": "O", "Care Instructions": "O", "Weight": "O", "Length": "O", "Breadth": "O", "Height": "O", "Bundles": "O", "Max Sale Quantity": "O", "Fragile": "O", "Liquid": "O", "Hazardous": "O", "Sub-Category": "Briefs", "Gender": "M", "Colour": "M", "Size": "M", "Fabric": "M", "Wash Type": "O", "Features": "O", "Fabric Finish": "O", "Material": "O", "Material Finish": "O", "Pattern": "O", "Occasion": "O", "Season": "O", "Trend": "O", "Fit": "O"}, {"Category": "Fashion", "Brand": "M", "Size Chart": "M", "Colour Name": "O", "Care Instructions": "O", "Weight": "O", "Length": "O", "Breadth": "O", "Height": "O", "Bundles": "O", "Max Sale Quantity": "O", "Fragile": "O", "Liquid": "O", "Hazardous": "O", "Sub-Category": "Boxers", "Gender": "M", "Colour": "M", "Size": "M", "Fabric": "M", "Wash Type": "O", "Features": "O", "Fabric Finish": "O", "Material": "O", "Material Finish": "O", "Pattern": "O", "Occasion": "O", "Season": "O", "Trend": "O", "Fit": "O"}, {"Category": "Fashion", "Brand": "M", "Size Chart": "M", "Colour Name": "O", "Care Instructions": "O", "Weight": "O", "Length": "O", "Breadth": "O", "Height": "O", "Bundles": "O", "Max Sale Quantity": "O", "Fragile": "O", "Liquid": "O", "Hazardous": "O", "Sub-Category": "Vests", "Gender": "M", "Colour": "M", "Size": "M", "Fabric": "M", "Wash Type": "O", "Features": "O", "Fabric Finish": "O", "Material": "O", "Material Finish": "O", "Pattern": "O", "Occasion": "O", "Season": "O", "Trend": "O", "Fit": "O"}, {"Category": "Fashion", "Brand": "M", "Size Chart": "M", "Colour Name": "O", "Care Instructions": "O", "Weight": "O", "Length": "O", "Breadth": "O", "Height": "O", "Bundles": "O", "Max Sale Quantity": "O", "Lining": "O", "Fragile": "O", "Liquid": "O", "Hazardous": "O", "Sub-Category": "Robes", "Gender": "M", "Colour": "M", "Size": "M", "Fabric": "M", "Wash Type": "O", "Features": "O", "Fabric Finish": "O", "Material": "O", "Material Finish": "O", "Pattern": "O", "Occasion": "O", "Season": "O", "Trend": "O", "Fit": "O"}, {"Category": "Fashion", "Brand": "M", "Size Chart": "M", "Colour Name": "O", "Care Instructions": "O", "Weight": "O", "Length": "O", "Breadth": "O", "Height": "O", "Bundles": "O", "Max Sale Quantity": "O", "Lining": "O", "Num Pockets": "O", "Fragile": "O", "Liquid": "O", "Hazardous": "O", "Sub-Category": "Night Suits", "Gender": "M", "Colour": "M", "Size": "M", "Fabric": "M", "Wash Type": "O", "Features": "O", "Fabric Finish": "O", "Material": "O", "Material Finish": "O", "Pattern": "O", "Occasion": "O", "Season": "O", "Trend": "O", "Fit": "O"}, {"Category": "Fashion", "Brand": "M", "Size Chart": "M", "Colour Name": "O", "Care Instructions": "O", "Weight": "O", "Length": "O", "Breadth": "O", "Height": "O", "Bundles": "O", "Max Sale Quantity": "O", "Lining": "O", "Fragile": "O", "Liquid": "O", "Hazardous": "O", "Sub-Category": "Thermal Wear", "Gender": "M", "Colour": "M", "Size": "M", "Fabric": "M", "Wash Type": "O", "Features": "O", "Fabric Finish": "O", "Material": "O", "Material Finish": "O", "Pattern": "O", "Occasion": "O", "Season": "O", "Trend": "O", "Fit": "O"}, {"Category": "Fashion", "Brand": "M", "Size Chart": "M", "Colour Name": "O", "Care Instructions": "O", "Weight": "O", "Length": "O", "Breadth": "O", "Height": "O", "Bundles": "O", "Max Sale Quantity": "O", "Fragile": "O", "Liquid": "O", "Hazardous": "O", "Sub-Category": "Swim Bottoms", "Gender": "M", "Colour": "M", "Size": "M", "Fabric": "M", "Wash Type": "O", "Features": "O", "Fabric Finish": "O", "Material": "O", "Material Finish": "O", "Pattern": "O", "Occasion": "O", "Season": "O", "Trend": "O", "Fit": "O"}, {"Category": "Fashion", "Brand": "M", "Size Chart": "M", "Colour Name": "O", "Care Instructions": "O", "Weight": "O", "Length": "O", "Breadth": "O", "Height": "O", "Bundles": "O", "Max Sale Quantity": "O", "Fragile": "O", "Liquid": "O", "Hazardous": "O", "Sub-Category": "Swimwear", "Gender": "M", "Colour": "M", "Size": "M", "Fabric": "M", "Wash Type": "O", "Features": "O", "Fabric Finish": "O", "Material": "O", "Material Finish": "O", "Pattern": "O", "Occasion": "O", "Season": "O", "Trend": "O", "Fit": "O"}, {"Category": "Fashion", "Brand": "M", "Size Chart": "M", "Colour Name": "O", "Care Instructions": "O", "Weight": "O", "Length": "O", "Breadth": "O", "Height": "O", "Bundles": "O", "Max Sale Quantity": "O", "Lining": "O", "Fragile": "O", "Liquid": "O", "Hazardous": "O", "Sub-Category": "Bra", "Gender": "M", "Colour": "M", "Size": "M", "Fabric": "M", "Wash Type": "O", "Features": "O", "Fabric Finish": "O", "Material": "O", "Material Finish": "O", "Pattern": "O", "Occasion": "O", "Season": "O", "Trend": "O", "Fit": "O", "Coverage": "O", "Padding": "O"}, {"Category": "Fashion", "Brand": "M", "Size Chart": "M", "Colour Name": "O", "Care Instructions": "O", "Weight": "O", "Length": "O", "Breadth": "O", "Height": "O", "Bundles": "O", "Max Sale Quantity": "O", "Lining": "O", "Fragile": "O", "Liquid": "O", "Hazardous": "O", "Sub-Category": "Shapewear", "Gender": "M", "Colour": "M", "Size": "M", "Fabric": "M", "Wash Type": "O", "Features": "O", "Fabric Finish": "O", "Material": "O", "Material Finish": "O", "Pattern": "O", "Occasion": "O", "Season": "O", "Trend": "O", "Fit": "O", "Coverage": "O", "Padding": "O"}, {"Category": "Fashion", "Brand": "M", "Size Chart": "M", "Colour Name": "O", "Care Instructions": "O", "Weight": "O", "Length": "O", "Breadth": "O", "Height": "O", "Bundles": "O", "Max Sale Quantity": "O", "Lining": "O", "Fragile": "O", "Liquid": "O", "Hazardous": "O", "Sub-Category": "Sleepwear & Loungewear", "Gender": "M", "Colour": "M", "Size": "M", "Fabric": "M", "Wash Type": "O", "Features": "O", "Fabric Finish": "O", "Material": "O", "Material Finish": "O", "Pattern": "O", "Occasion": "O", "Season": "O", "Trend": "O", "Fit": "O"}, {"Category": "Fashion", "Brand": "M", "Size Chart": "M", "Colour Name": "O", "Care Instructions": "O", "Weight": "O", "Length": "O", "Breadth": "O", "Height": "O", "Bundles": "O", "Max Sale Quantity": "O", "Lining": "O", "Fragile": "O", "Liquid": "O", "Hazardous": "O", "Sub-Category": "Camisoles", "Gender": "M", "Colour": "M", "Size": "M", "Fabric": "M", "Wash Type": "O", "Features": "O", "Fabric Finish": "O", "Material": "O", "Material Finish": "O", "Pattern": "O", "Occasion": "O", "Season": "O", "Trend": "O", "Fit": "O"}, {"Category": "Fashion", "Brand": "M", "Size Chart": "M", "Colour Name": "O", "Care Instructions": "O", "Weight": "O", "Length": "O", "Breadth": "O", "Height": "O", "Bundles": "O", "Max Sale Quantity": "O", "Lining": "O", "Fragile": "O", "Liquid": "O", "Hazardous": "O", "Sub-Category": "Lingerie Sets & Accessories", "Gender": "M", "Colour": "M", "Size": "M", "Fabric": "M", "Wash Type": "O", "Features": "O", "Fabric Finish": "O", "Material": "O", "Material Finish": "O", "Pattern": "O", "Occasion": "O", "Season": "O", "Trend": "O", "Fit": "O", "Coverage": "O", "Padding": "O"}, {"Category": "Fashion", "Brand": "M", "Size Chart": "M", "Colour Name": "O", "Care Instructions": "O", "Weight": "O", "Length": "O", "Breadth": "O", "Height": "O", "Bundles": "O", "Max Sale Quantity": "O", "Lining": "O", "Fragile": "O", "Liquid": "O", "Hazardous": "O", "Sub-Category": "Bath Robes", "Gender": "M", "Colour": "M", "Size": "M", "Fabric": "M", "Wash Type": "O", "Features": "O", "Fabric Finish": "O", "Material": "O", "Material Finish": "O", "Pattern": "O", "Occasion": "O", "Season": "O", "Trend": "O", "Fit": "O"}, {"Category": "Fashion", "Brand": "M", "Colour Name": "O", "Care Instructions": "O", "Weight": "O", "Length": "O", "Breadth": "O", "Height": "O", "Bundles": "O", "Max Sale Quantity": "O", "Fragile": "O", "Liquid": "O", "Hazardous": "O", "Sub-Category": "Towels", "Gender": "M", "Colour": "M", "Size": "M", "Wash Type": "O", "Features": "O", "Material": "O", "Material Finish": "O", "Pattern": "O", "Occasion": "O", "Season": "O", "Trend": "O"}, {"Category": "Fashion", "Brand": "M", "Size Chart": "M", "Colour Name": "O", "Care Instructions": "O", "Weight": "O", "Length": "O", "Breadth": "O", "Height": "O", "Bundles": "O", "Max Sale Quantity": "O", "Lining": "O", "Num Pockets": "O", "Fragile": "O", "Liquid": "O", "Hazardous": "O", "Sub-Category": "Pyjamas", "Gender": "M", "Colour": "M", "Size": "M", "Fabric": "M", "Wash Type": "O", "Features": "O", "Fabric Finish": "O", "Material": "O", "Material Finish": "O", "Pattern": "O", "Occasion": "O", "Season": "O", "Trend": "O", "Fit": "O"}, {"Category": "Fashion", "Brand": "M", "Size Chart": "M", "Colour Name": "O", "Care Instructions": "O", "Weight": "O", "Length": "O", "Breadth": "O", "Height": "O", "Bundles": "O", "Max Sale Quantity": "O", "Num Pockets": "O", "Fragile": "O", "Liquid": "O", "Hazardous": "O", "Sub-Category": "Party Wear", "Gender": "M", "Colour": "M", "Size": "M", "Fabric": "M", "Wash Type": "O", "Features": "O", "Fabric Finish": "O", "Material": "O", "Material Finish": "O", "Pattern": "O", "Occasion": "O", "Season": "O", "Trend": "O", "Fit": "O", "Collar": "O", "Neck": "O", "Sleeve Length": "O", "Ornamentation": "O"}, {"Category": "Fashion", "Brand": "M", "Size Chart": "M", "Colour Name": "O", "Care Instructions": "O", "Weight": "O", "Length": "O", "Breadth": "O", "Height": "O", "Bundles": "O", "Max Sale Quantity": "O", "Num Pockets": "O", "Fragile": "O", "Liquid": "O", "Hazardous": "O", "Sub-Category": "Innerwear & Sleepwear", "Gender": "M", "Colour": "M", "Size": "M", "Fabric": "M", "Wash Type": "O", "Features": "O", "Fabric Finish": "O", "Material": "O", "Material Finish": "O", "Pattern": "O", "Occasion": "O", "Season": "O", "Trend": "O", "Fit": "O", "Collar": "O", "Neck": "O", "Sleeve Length": "O", "Closure Type": "O", "Strap Type": "O", "Coverage": "O", "Padding": "O", "Seam": "O", "Waist Band": "O"}, {"Category": "Fashion", "Brand": "M", "Size Chart": "M", "Colour Name": "O", "Care Instructions": "O", "Weight": "O", "Length": "O", "Breadth": "O", "Height": "O", "Bundles": "O", "Max Sale Quantity": "O", "Num Pockets": "O", "Fragile": "O", "Liquid": "O", "Hazardous": "O", "Sub-Category": "Nightwear & Loungewear", "Gender": "M", "Colour": "M", "Size": "M", "Fabric": "M", "Wash Type": "O", "Features": "O", "Fabric Finish": "O", "Material": "O", "Material Finish": "O", "Pattern": "O", "Occasion": "O", "Season": "O", "Trend": "O", "Fit": "O", "Collar": "O", "Neck": "O", "Sleeve Length": "O"}, {"Category": "Fashion", "Brand": "M", "Water Resistant": "M", "Colour Name": "O", "Care Instructions": "O", "Weight": "O", "Length": "O", "Breadth": "O", "Height": "O", "Bundles": "O", "Max Sale Quantity": "O", "Fragile": "O", "Liquid": "O", "Hazardous": "O", "Battery Life": "O", "Bluetooth": "O", "Call Function": "O", "Heart Rate Monitor": "O", "Pedometer": "O", "Sleep Monitor": "O", "SPO2 Monitor": "O", "Warranty": "O", "Sub-Category": "Watches", "Gender": "M", "Colour": "M", "Size": "M", "Strap Material": "M", "Display": "M", "Glass Material": "M", "Features": "O", "Material Finish": "O", "Pattern": "O", "Occasion": "O", "Season": "O", "Trend": "O", "Power Type": "O", "Buckle Material": "O", "Buckle Type": "O", "Dial Shape": "O"}, {"Category": "Fashion", "Brand": "M", "Colour Name": "O", "Care Instructions": "O", "Weight": "O", "Length": "O", "Breadth": "O", "Height": "O", "Bundles": "O", "Max Sale Quantity": "O", "Fragile": "O", "Liquid": "O", "Hazardous": "O", "Sub-Category": "Gloves", "Gender": "M", "Colour": "M", "Size": "M", "Features": "O", "Material": "O", "Material Finish": "O", "Pattern": "O", "Occasion": "O", "Season": "O", "Trend": "O"}, {"Category": "Fashion", "Brand": "M", "Size Chart": "M", "Colour Name": "O", "Care Instructions": "O", "Weight": "O", "Length": "O", "Breadth": "O", "Height": "O", "Bundles": "O", "Max Sale Quantity": "O", "Fragile": "O", "Liquid": "O", "Hazardous": "O", "Sub-Category": "Socks", "Gender": "M", "Colour": "M", "Size": "M", "Fabric": "M", "Features": "O", "Fabric Finish": "O", "Material": "O", "Material Finish": "O", "Pattern": "O", "Occasion": "O", "Season": "O", "Trend": "O", "Socks Length": "O"}, {"Category": "Fashion", "Brand": "M", "Colour Name": "O", "Care Instructions": "O", "Weight": "O", "Length": "O", "Breadth": "O", "Height": "O", "Bundles": "O", "Max Sale Quantity": "O", "Fragile": "O", "Liquid": "O", "Hazardous": "O", "Sub-Category": "Stockings", "Gender": "M", "Colour": "M", "Size": "M", "Fabric": "M", "Features": "O", "Fabric Finish": "O", "Material": "O", "Material Finish": "O", "Pattern": "O", "Occasion": "O", "Season": "O", "Trend": "O"}, {"Category": "Fashion", "Brand": "M", "Colour Name": "O", "Care Instructions": "O", "Weight": "O", "Length": "O", "Breadth": "O", "Height": "O", "Bundles": "O", "Max Sale Quantity": "O", "Fragile": "O", "Liquid": "O", "Hazardous": "O", "Sub-Category": "Laces", "Gender": "M", "Colour": "M", "Size": "M", "Fabric": "M", "Features": "O", "Fabric Finish": "O", "Material": "O", "Material Finish": "O", "Pattern": "O", "Occasion": "O", "Season": "O", "Trend": "O"}, {"Category": "Fashion", "Brand": "M", "Colour Name": "O", "Care Instructions": "O", "Weight": "O", "Length": "O", "Breadth": "O", "Height": "O", "Bundles": "O", "Max Sale Quantity": "O", "Fragile": "O", "Liquid": "O", "Hazardous": "O", "Sub-Category": "Soles & Charms", "Gender": "M", "Colour": "M", "Size": "M", "Features": "O", "Material": "O", "Material Finish": "O", "Pattern": "O", "Occasion": "O", "Season": "O", "Trend": "O"}, {"Category": "Fashion", "Brand": "M", "Colour Name": "O", "Care Instructions": "O", "Weight": "O", "Length": "O", "Breadth": "O", "Height": "O", "Bundles": "O", "Max Sale Quantity": "O", "Fragile": "O", "Liquid": "O", "Hazardous": "O", "Sub-Category": "Shoe Racks & Organisers", "Gender": "M", "Colour": "M", "Size": "M", "Features": "O", "Material": "O", "Material Finish": "O", "Pattern": "O", "Occasion": "O", "Season": "O", "Trend": "O"}, {"Category": "Fashion", "Brand": "M", "Colour Name": "O", "Care Instructions": "O", "Weight": "O", "Length": "O", "Breadth": "O", "Height": "O", "Bundles": "O", "Max Sale Quantity": "O", "Fragile": "O", "Liquid": "O", "Hazardous": "O", "Sub-Category": "Shoe Care - Accessories", "Gender": "M", "Colour": "M", "Size": "M", "Features": "O", "Material": "O", "Material Finish": "O", "Pattern": "O", "Occasion": "O", "Season": "O", "Trend": "O"}, {"Category": "Fashion", "Brand": "M", "Size Chart": "M", "Colour Name": "O", "Care Instructions": "O", "Weight": "O", "Length": "O", "Breadth": "O", "Height": "O", "Bundles": "O", "Max Sale Quantity": "O", "Fragile": "O", "Liquid": "O", "Hazardous": "O", "Sub-Category": "Flip-Flops & Flats", "Gender": "M", "Colour": "M", "Size": "M", "Fabric": "M", "Features": "O", "Fabric Finish": "O", "Material": "O", "Material Finish": "O", "Pattern": "O", "Occasion": "O", "Season": "O", "Trend": "O", "Footwear Type": "O", "Insole": "O", "Sole Material": "O", "Toe Shape": "O", "Outsole": "O", "Fasten Type": "O", "Midsole": "O"}, {"Category": "Fashion", "Brand": "M", "Size Chart": "M", "Colour Name": "O", "Care Instructions": "O", "Weight": "O", "Length": "O", "Breadth": "O", "Height": "O", "Bundles": "O", "Max Sale Quantity": "O", "Fragile": "O", "Liquid": "O", "Hazardous": "O", "Sub-Category": "Sandals & Floaters", "Gender": "M", "Colour": "M", "Size": "M", "Fabric": "M", "Features": "O", "Fabric Finish": "O", "Material": "O", "Material Finish": "O", "Pattern": "O", "Occasion": "O", "Season": "O", "Trend": "O", "Footwear Type": "O", "Insole": "O", "Sole Material": "O", "Toe Shape": "O", "Outsole": "O", "Fasten Type": "O", "Midsole": "O"}, {"Category": "Fashion", "Brand": "M", "Water Resistant": "O", "Colour Name": "O", "Care Instructions": "O", "Weight": "O", "Length": "O", "Breadth": "O", "Height": "O", "Bundles": "O", "Max Sale Quantity": "O", "Lining": "O", "Num Pockets": "O", "Fragile": "O", "Liquid": "O", "Hazardous": "O", "Laptop Compartment": "O", "Volume": "O", "Sub-Category": "Backpacks", "Gender": "M", "Colour": "M", "Size": "M", "Fabric": "M", "Features": "O", "Fabric Finish": "O", "Material": "O", "Material Finish": "O", "Pattern": "O", "Occasion": "O", "Season": "O", "Trend": "O", "Backpack Style": "O", "Closure Type": "O", "Strap Type": "O", "Lock Type": "O"}, {"Category": "Fashion", "Brand": "M", "Water Resistant": "O", "Colour Name": "O", "Care Instructions": "O", "Weight": "O", "Length": "O", "Breadth": "O", "Height": "O", "Bundles": "O", "Max Sale Quantity": "O", "Lining": "O", "Num Pockets": "O", "Fragile": "O", "Liquid": "O", "Hazardous": "O", "Laptop Compartment": "O", "Volume": "O", "Sustainability": "O", "Handcrafted": "O", "Craftmark": "O", "Sub-Category": "Handbags", "Gender": "M", "Colour": "M", "Size": "M", "Features": "O", "Material": "O", "Material Finish": "O", "Pattern": "O", "Occasion": "O", "Season": "O", "Trend": "O", "Closure Type": "O", "Strap Type": "O", "Lock Type": "O"}, {"Category": "Fashion", "Brand": "M", "Water Resistant": "O", "Colour Name": "O", "Care Instructions": "O", "Weight": "O", "Length": "O", "Breadth": "O", "Height": "O", "Bundles": "O", "Max Sale Quantity": "O", "Lining": "O", "Num Pockets": "O", "Fragile": "O", "Liquid": "O", "Hazardous": "O", "Laptop Compartment": "O", "Volume": "O", "Sub-Category": "Trolley, Luggage & Suitcases", "Gender": "M", "Colour": "M", "Size": "M", "Fabric": "M", "Features": "O", "Fabric Finish": "O", "Material": "O", "Material Finish": "O", "Pattern": "O", "Occasion": "O", "Season": "O", "Trend": "O", "Closure Type": "O", "Strap Type": "O", "Lock Type": "O"}, {"Category": "Fashion", "Brand": "M", "Size Chart": "M", "Colour Name": "O", "Care Instructions": "O", "Weight": "O", "Length": "O", "Breadth": "O", "Height": "O", "Bundles": "O", "Max Sale Quantity": "O", "Fragile": "O", "Liquid": "O", "Hazardous": "O", "Sub-Category": "Formal Shoes", "Gender": "M", "Colour": "M", "Size": "M", "Fabric": "M", "Features": "O", "Fabric Finish": "O", "Material": "O", "Material Finish": "O", "Pattern": "O", "Occasion": "O", "Season": "O", "Trend": "O", "Footwear Type": "O", "Insole": "O", "Sole Material": "O", "Toe Shape": "O", "Outsole": "O", "Fasten Type": "O", "Midsole": "O"}, {"Category": "Fashion", "Brand": "M", "Size Chart": "M", "Colour Name": "O", "Care Instructions": "O", "Weight": "O", "Length": "O", "Breadth": "O", "Height": "O", "Bundles": "O", "Max Sale Quantity": "O", "Fragile": "O", "Liquid": "O", "Hazardous": "O", "Sub-Category": "Casual Shoes", "Gender": "M", "Colour": "M", "Size": "M", "Fabric": "M", "Features": "O", "Fabric Finish": "O", "Material": "O", "Material Finish": "O", "Pattern": "O", "Occasion": "O", "Season": "O", "Trend": "O", "Footwear Type": "O", "Insole": "O", "Sole Material": "O", "Toe Shape": "O", "Outsole": "O", "Fasten Type": "O", "Midsole": "O"}, {"Category": "Fashion", "Brand": "M", "Size Chart": "M", "Colour Name": "O", "Care Instructions": "O", "Weight": "O", "Length": "O", "Breadth": "O", "Height": "O", "Bundles": "O", "Max Sale Quantity": "O", "Fragile": "O", "Liquid": "O", "Hazardous": "O", "Sub-Category": "Sports Shoes", "Gender": "M", "Colour": "M", "Size": "M", "Fabric": "M", "Sport Type": "M", "Features": "O", "Fabric Finish": "O", "Material": "O", "Material Finish": "O", "Pattern": "O", "Occasion": "O", "Season": "O", "Trend": "O", "Footwear Type": "O", "Insole": "O", "Sole Material": "O", "Toe Shape": "O", "Outsole": "O", "Fasten Type": "O", "Midsole": "O"}, {"Category": "Fashion", "Brand": "M", "Size Chart": "M", "Colour Name": "O", "Care Instructions": "O", "Weight": "O", "Length": "O", "Breadth": "O", "Height": "O", "Bundles": "O", "Max Sale Quantity": "O", "Fragile": "O", "Liquid": "O", "Hazardous": "O", "Sub-Category": "Outdoor Shoes", "Gender": "M", "Colour": "M", "Size": "M", "Features": "O", "Material": "O", "Material Finish": "O", "Pattern": "O", "Occasion": "O", "Season": "O", "Trend": "O", "Footwear Type": "O", "Insole": "O", "Sole Material": "O", "Toe Shape": "O", "Outsole": "O", "Fasten Type": "O", "Midsole": "O"}, {"Category": "Fashion", "Brand": "M", "Size Chart": "M", "Colour Name": "O", "Care Instructions": "O", "Weight": "O", "Length": "O", "Breadth": "O", "Height": "O", "Bundles": "O", "Max Sale Quantity": "O", "Fragile": "O", "Liquid": "O", "Hazardous": "O", "Sub-Category": "Work & Safety Shoes", "Gender": "M", "Colour": "M", "Size": "M", "Features": "O", "Material": "O", "Material Finish": "O", "Pattern": "O", "Occasion": "O", "Season": "O", "Trend": "O", "Footwear Type": "O", "Insole": "O", "Sole Material": "O", "Toe Shape": "O", "Outsole": "O", "Fasten Type": "O", "Midsole": "O"}, {"Category": "Fashion", "Brand": "M", "Size Chart": "M", "Colour Name": "O", "Care Instructions": "O", "Weight": "O", "Length": "O", "Breadth": "O", "Height": "O", "Bundles": "O", "Max Sale Quantity": "O", "Fragile": "O", "Liquid": "O", "Hazardous": "O", "Sub-Category": "Ethnic Shoes", "Gender": "M", "Colour": "M", "Size": "M", "Fabric": "M", "Features": "O", "Fabric Finish": "O", "Material": "O", "Material Finish": "O", "Pattern": "O", "Occasion": "O", "Season": "O", "Trend": "O", "Footwear Type": "O", "Insole": "O", "Sole Material": "O", "Toe Shape": "O", "Outsole": "O", "Fasten Type": "O", "Midsole": "O"}, {"Category": "Fashion", "Brand": "M", "Size Chart": "M", "Colour Name": "O", "Care Instructions": "O", "Weight": "O", "Length": "O", "Breadth": "O", "Height": "O", "Bundles": "O", "Max Sale Quantity": "O", "Fragile": "O", "Liquid": "O", "Hazardous": "O", "Sub-Category": "Boots", "Gender": "M", "Colour": "M", "Size": "M", "Features": "O", "Material": "O", "Material Finish": "O", "Pattern": "O", "Occasion": "O", "Season": "O", "Trend": "O", "Footwear Type": "O", "Insole": "O", "Sole Material": "O", "Toe Shape": "O", "Outsole": "O", "Fasten Type": "O", "Midsole": "O"}, {"Category": "Fashion", "Brand": "M", "Size Chart": "M", "Colour Name": "O", "Care Instructions": "O", "Weight": "O", "Length": "O", "Breadth": "O", "Height": "O", "Bundles": "O", "Max Sale Quantity": "O", "Fragile": "O", "Liquid": "O", "Hazardous": "O", "Sub-Category": "Heels", "Gender": "M", "Colour": "M", "Size": "M", "Fabric": "M", "Features": "O", "Fabric Finish": "O", "Material": "O", "Material Finish": "O", "Pattern": "O", "Occasion": "O", "Season": "O", "Trend": "O", "Footwear Type": "O", "Insole": "O", "Sole Material": "O", "Toe Shape": "O", "Outsole": "O", "Fasten Type": "O", "Midsole": "O"}, {"Category": "Fashion", "Brand": "M", "Colour Name": "O", "Care Instructions": "O", "Weight": "O", "Length": "O", "Breadth": "O", "Height": "O", "Bundles": "O", "Max Sale Quantity": "O", "Fragile": "O", "Liquid": "O", "Hazardous": "O", "Sub-Category": "Contact Lenses", "Gender": "M", "Colour": "M", "Size": "M", "Features": "O", "Material": "O", "Material Finish": "O", "Pattern": "O", "Occasion": "O", "Season": "O", "Trend": "O", "Lens Material": "O", "Lens Colour": "O"}, {"Category": "Fashion", "Brand": "M", "Colour Name": "O", "Care Instructions": "O", "Weight": "O", "Length": "O", "Breadth": "O", "Height": "O", "Bundles": "O", "Max Sale Quantity": "O", "Fragile": "O", "Liquid": "O", "Hazardous": "O", "Sub-Category": "Eye Glasses", "Gender": "M", "Colour": "M", "Size": "M", "Features": "O", "Material Finish": "O", "Pattern": "O", "Occasion": "O", "Season": "O", "Trend": "O", "Frame Type": "O", "Frame Shape": "O", "Frame Colour": "O", "Frame Size": "O", "Frame Material": "O", "Frame Style": "O", "Face Shape": "O", "Lens Material": "O", "Lens Colour": "O"}, {"Category": "Fashion", "Brand": "M", "Colour Name": "O", "Care Instructions": "O", "Weight": "O", "Length": "O", "Breadth": "O", "Height": "O", "Bundles": "O", "Max Sale Quantity": "O", "Fragile": "O", "Liquid": "O", "Hazardous": "O", "Sub-Category": "Eye Glass Frames", "Gender": "M", "Colour": "M", "Size": "M", "Features": "O", "Material Finish": "O", "Pattern": "O", "Occasion": "O", "Season": "O", "Trend": "O", "Frame Type": "O", "Frame Shape": "O", "Frame Colour": "O", "Frame Size": "O", "Frame Material": "O", "Frame Style": "O", "Face Shape": "O", "Lens Material": "O", "Lens Colour": "O"}, {"Category": "Fashion", "Brand": "M", "Colour Name": "O", "Care Instructions": "O", "Weight": "O", "Length": "O", "Breadth": "O", "Height": "O", "Bundles": "O", "Max Sale Quantity": "O", "Fragile": "O", "Liquid": "O", "Hazardous": "O", "Sub-Category": "Sunglasses", "Gender": "M", "Colour": "M", "Size": "M", "Features": "O", "Material Finish": "O", "Pattern": "O", "Occasion": "O", "Season": "O", "Trend": "O", "Frame Type": "O", "Frame Shape": "O", "Frame Colour": "O", "Frame Size": "O", "Frame Material": "O", "Frame Style": "O", "Face Shape": "O", "Lens Material": "O", "Lens Colour": "O"}, {"Category": "Fashion", "Brand": "M", "Colour Name": "O", "Care Instructions": "O", "Weight": "O", "Length": "O", "Breadth": "O", "Height": "O", "Bundles": "O", "Max Sale Quantity": "O", "Fragile": "O", "Liquid": "O", "Hazardous": "O", "Sub-Category": "Contact Lens Cases", "Gender": "M", "Colour": "M", "Size": "M", "Features": "O", "Material Finish": "O", "Pattern": "O", "Occasion": "O", "Season": "O", "Trend": "O"}, {"Category": "Fashion", "Brand": "M", "Colour Name": "O", "Care Instructions": "O", "Weight": "O", "Length": "O", "Breadth": "O", "Height": "O", "Bundles": "O", "Max Sale Quantity": "O", "Fragile": "O", "Liquid": "O", "Hazardous": "O", "Sub-Category": "Contact Lens Solutions", "Gender": "M", "Colour": "M", "Size": "M", "Features": "O", "Material Finish": "O", "Pattern": "O", "Occasion": "O", "Season": "O", "Trend": "O"}, {"Category": "Fashion", "Brand": "M", "Colour Name": "O", "Care Instructions": "O", "Weight": "O", "Length": "O", "Breadth": "O", "Height": "O", "Bundles": "O", "Max Sale Quantity": "O", "Fragile": "O", "Liquid": "O", "Hazardous": "O", "Sub-Category": "Contact Lens Tweezers", "Gender": "M", "Colour": "M", "Size": "M", "Features": "O", "Material": "O", "Material Finish": "O", "Pattern": "O", "Occasion": "O", "Season": "O", "Trend": "O"}, {"Category": "Fashion", "Brand": "M", "Colour Name": "O", "Care Instructions": "O", "Weight": "O", "Length": "O", "Breadth": "O", "Height": "O", "Bundles": "O", "Max Sale Quantity": "O", "Fragile": "O", "Liquid": "O", "Hazardous": "O", "Sub-Category": "Eyeglasses Pouches & Cases", "Gender": "M", "Colour": "M", "Size": "M", "Features": "O", "Material": "O", "Material Finish": "O", "Pattern": "O", "Occasion": "O", "Season": "O", "Trend": "O"}, {"Category": "Fashion", "Brand": "M", "Colour Name": "O", "Care Instructions": "O", "Weight": "O", "Length": "O", "Breadth": "O", "Height": "O", "Bundles": "O", "Max Sale Quantity": "O", "Fragile": "O", "Liquid": "O", "Hazardous": "O", "Sub-Category": "Microfiber Wipes", "Gender": "M", "Colour": "M", "Size": "M", "Features": "O", "Material": "O", "Material Finish": "O", "Pattern": "O", "Occasion": "O", "Season": "O", "Trend": "O"}, {"Category": "Fashion", "Brand": "M", "Colour Name": "O", "Care Instructions": "O", "Weight": "O", "Length": "O", "Breadth": "O", "Height": "O", "Bundles": "O", "Max Sale Quantity": "O", "Fragile": "O", "Liquid": "O", "Hazardous": "O", "Sub-Category": "Eyewear Slings", "Gender": "M", "Colour": "M", "Size": "M", "Features": "O", "Material": "O", "Material Finish": "O", "Pattern": "O", "Occasion": "O", "Season": "O", "Trend": "O"}, {"Category": "Fashion", "Brand": "M", "Colour Name": "O", "Care Instructions": "O", "Weight": "O", "Length": "O", "Breadth": "O", "Height": "O", "Bundles": "O", "Max Sale Quantity": "O", "Fragile": "O", "Liquid": "O", "Hazardous": "O", "Sustainability": "O", "Handcrafted": "O", "Craftmark": "O", "Sub-Category": "Bracelets", "Gender": "M", "Colour": "M", "Size": "M", "Base Metal": "M", "Plating": "M", "Features": "O", "Material": "O", "Material Finish": "O", "Pattern": "O", "Occasion": "O", "Season": "O", "Trend": "O", "Closure Type": "O", "Stone Type": "O", "Gem Type": "O"}, {"Category": "Fashion", "Brand": "M", "Colour Name": "O", "Care Instructions": "O", "Weight": "O", "Length": "O", "Breadth": "O", "Height": "O", "Bundles": "O", "Max Sale Quantity": "O", "Fragile": "O", "Liquid": "O", "Hazardous": "O", "Sustainability": "O", "Handcrafted": "O", "Craftmark": "O", "Sub-Category": "Chains", "Gender": "M", "Colour": "M", "Size": "M", "Base Metal": "M", "Plating": "M", "Features": "O", "Material": "O", "Material Finish": "O", "Pattern": "O", "Occasion": "O", "Season": "O", "Trend": "O", "Closure Type": "O", "Stone Type": "O", "Gem Type": "O"}, {"Category": "Fashion", "Brand": "M", "Colour Name": "O", "Care Instructions": "O", "Weight": "O", "Length": "O", "Breadth": "O", "Height": "O", "Bundles": "O", "Max Sale Quantity": "O", "Fragile": "O", "Liquid": "O", "Hazardous": "O", "Sustainability": "O", "Handcrafted": "O", "Craftmark": "O", "Sub-Category": "Mangalsutra", "Gender": "M", "Colour": "M", "Size": "M", "Base Metal": "M", "Plating": "M", "Features": "O", "Material": "O", "Material Finish": "O", "Pattern": "O", "Occasion": "O", "Season": "O", "Trend": "O", "Closure Type": "O", "Stone Type": "O", "Gem Type": "O"}, {"Category": "Fashion", "Brand": "M", "Colour Name": "O", "Care Instructions": "O", "Weight": "O", "Length": "O", "Breadth": "O", "Height": "O", "Bundles": "O", "Max Sale Quantity": "O", "Fragile": "O", "Liquid": "O", "Hazardous": "O", "Sustainability": "O", "Handcrafted": "O", "Craftmark": "O", "Sub-Category": "Anklets", "Gender": "M", "Colour": "M", "Size": "M", "Base Metal": "M", "Plating": "M", "Features": "O", "Material": "O", "Material Finish": "O", "Pattern": "O", "Occasion": "O", "Season": "O", "Trend": "O", "Closure Type": "O", "Stone Type": "O", "Gem Type": "O"}, {"Category": "Fashion", "Brand": "M", "Colour Name": "O", "Care Instructions": "O", "Weight": "O", "Length": "O", "Breadth": "O", "Height": "O", "Bundles": "O", "Max Sale Quantity": "O", "Fragile": "O", "Liquid": "O", "Hazardous": "O", "Sustainability": "O", "Handcrafted": "O", "Craftmark": "O", "Sub-Category": "Bangles & Bracelets", "Gender": "M", "Colour": "M", "Size": "M", "Base Metal": "O", "Plating": "O", "Features": "O", "Material": "O", "Material Finish": "O", "Pattern": "O", "Occasion": "O", "Season": "O", "Trend": "O", "Closure Type": "O", "Stone Type": "O", "Gem Type": "O"}, {"Category": "Fashion", "Brand": "M", "Colour Name": "O", "Care Instructions": "O", "Weight": "O", "Length": "O", "Breadth": "O", "Height": "O", "Bundles": "O", "Max Sale Quantity": "O", "Fragile": "O", "Liquid": "O", "Hazardous": "O", "Sustainability": "O", "Handcrafted": "O", "Craftmark": "O", "Sub-Category": "Necklaces", "Gender": "M", "Colour": "M", "Size": "M", "Base Metal": "M", "Plating": "M", "Features": "O", "Material": "O", "Material Finish": "O", "Pattern": "O", "Occasion": "O", "Season": "O", "Trend": "O", "Closure Type": "O", "Stone Type": "O", "Gem Type": "O"}, {"Category": "Fashion", "Brand": "M", "Colour Name": "O", "Care Instructions": "O", "Weight": "O", "Length": "O", "Breadth": "O", "Height": "O", "Bundles": "O", "Max Sale Quantity": "O", "Fragile": "O", "Liquid": "O", "Hazardous": "O", "Sustainability": "O", "Handcrafted": "O", "Craftmark": "O", "Sub-Category": "Earrings", "Gender": "M", "Colour": "M", "Size": "M", "Base Metal": "M", "Plating": "M", "Features": "O", "Material": "O", "Material Finish": "O", "Pattern": "O", "Occasion": "O", "Season": "O", "Trend": "O", "Closure Type": "O", "Stone Type": "O", "Gem Type": "O"}, {"Category": "Fashion", "Brand": "M", "Colour Name": "O", "Care Instructions": "O", "Weight": "O", "Length": "O", "Breadth": "O", "Height": "O", "Bundles": "O", "Max Sale Quantity": "O", "Fragile": "O", "Liquid": "O", "Hazardous": "O", "Sustainability": "O", "Handcrafted": "O", "Craftmark": "O", "Sub-Category": "Jewellery Sets", "Gender": "M", "Colour": "M", "Size": "M", "Base Metal": "M", "Plating": "M", "Features": "O", "Material": "O", "Material Finish": "O", "Pattern": "O", "Occasion": "O", "Season": "O", "Trend": "O", "Closure Type": "O", "Stone Type": "O", "Gem Type": "O"}, {"Category": "Fashion", "Brand": "M", "Colour Name": "O", "Care Instructions": "O", "Weight": "O", "Length": "O", "Breadth": "O", "Height": "O", "Bundles": "O", "Max Sale Quantity": "O", "Fragile": "O", "Liquid": "O", "Hazardous": "O", "Sustainability": "O", "Handcrafted": "O", "Craftmark": "O", "Sub-Category": "Nosepins & Noserings", "Gender": "M", "Colour": "M", "Size": "M", "Base Metal": "M", "Plating": "M", "Features": "O", "Material": "O", "Material Finish": "O", "Pattern": "O", "Occasion": "O", "Season": "O", "Trend": "O", "Closure Type": "O", "Stone Type": "O", "Gem Type": "O"}, {"Category": "Fashion", "Brand": "M", "Colour Name": "O", "Care Instructions": "O", "Weight": "O", "Length": "O", "Breadth": "O", "Height": "O", "Bundles": "O", "Max Sale Quantity": "O", "Fragile": "O", "Liquid": "O", "Hazardous": "O", "Sustainability": "O", "Handcrafted": "O", "Craftmark": "O", "Sub-Category": "Pendants", "Gender": "M", "Colour": "M", "Size": "M", "Base Metal": "M", "Plating": "M", "Features": "O", "Material": "O", "Material Finish": "O", "Pattern": "O", "Occasion": "O", "Season": "O", "Trend": "O", "Closure Type": "O", "Stone Type": "O", "Gem Type": "O"}, {"Category": "Fashion", "Brand": "M", "Colour Name": "O", "Care Instructions": "O", "Weight": "O", "Length": "O", "Breadth": "O", "Height": "O", "Bundles": "O", "Max Sale Quantity": "O", "Fragile": "O", "Liquid": "O", "Hazardous": "O", "Sustainability": "O", "Handcrafted": "O", "Craftmark": "O", "Sub-Category": "Rings", "Gender": "M", "Colour": "M", "Size": "M", "Base Metal": "M", "Plating": "M", "Features": "O", "Material": "O", "Material Finish": "O", "Pattern": "O", "Occasion": "O", "Season": "O", "Trend": "O", "Closure Type": "O", "Stone Type": "O", "Gem Type": "O"}, {"Category": "Fashion", "Brand": "M", "Colour Name": "O", "Care Instructions": "O", "Weight": "O", "Length": "O", "Breadth": "O", "Height": "O", "Bundles": "O", "Max Sale Quantity": "O", "Fragile": "O", "Liquid": "O", "Hazardous": "O", "Sustainability": "O", "Handcrafted": "O", "Craftmark": "O", "Sub-Category": "Toe Rings", "Gender": "M", "Colour": "M", "Size": "M", "Base Metal": "M", "Plating": "M", "Features": "O", "Material": "O", "Material Finish": "O", "Pattern": "O", "Occasion": "O", "Season": "O", "Trend": "O", "Closure Type": "O", "Stone Type": "O", "Gem Type": "O"}, {"Category": "Fashion", "Brand": "M", "Colour Name": "O", "Care Instructions": "O", "Weight": "O", "Length": "O", "Breadth": "O", "Height": "O", "Bundles": "O", "Max Sale Quantity": "O", "Fragile": "O", "Liquid": "O", "Hazardous": "O", "Sustainability": "O", "Handcrafted": "O", "Craftmark": "O", "Sub-Category": "Gold Coins", "Gender": "M", "Colour": "M", "Size": "M", "Base Metal": "M", "Plating": "M", "Features": "O", "Material": "O", "Material Finish": "O", "Pattern": "O", "Occasion": "O", "Season": "O", "Trend": "O", "Closure Type": "O", "Stone Type": "O", "Gem Type": "O"}, {"Category": "Fashion", "Brand": "M", "Colour Name": "O", "Care Instructions": "O", "Weight": "O", "Length": "O", "Breadth": "O", "Height": "O", "Bundles": "O", "Max Sale Quantity": "O", "Fragile": "O", "Liquid": "O", "Hazardous": "O", "Sustainability": "O", "Handcrafted": "O", "Craftmark": "O", "Sub-Category": "Brooch", "Gender": "M", "Colour": "M", "Size": "M", "Base Metal": "M", "Plating": "M", "Features": "O", "Material": "O", "Material Finish": "O", "Pattern": "O", "Occasion": "O", "Season": "O", "Trend": "O", "Closure Type": "O", "Stone Type": "O", "Gem Type": "O"}]